gdtchron/__init__.py
gdtchron/_parallel_vtk.py
gdtchron/_visualization.py
gdtchron/aft.py
gdtchron/he.py
gdtchron-0.1.0.dist-info/LICENSE
gdtchron-0.1.0.dist-info/METADATA
gdtchron-0.1.0.dist-info/WHEEL
gdtchron-0.1.0.dist-info/RECORD
