Metadata-Version: 2.3
Name: gdtchron
Version: 0.1.0
Summary: Thermochronology for geodynamic models
License: MIT
Author: Dylan Vasey
Author-email: dylan.vasey@tufts.edu
Requires-Python: >=3.9,<4.0
Classifier: License :: OSI Approved :: MIT License
Classifier: Programming Language :: Python :: 3
Classifier: Programming Language :: Python :: 3.9
Classifier: Programming Language :: Python :: 3.10
Classifier: Programming Language :: Python :: 3.11
Classifier: Programming Language :: Python :: 3.12
Classifier: Programming Language :: Python :: 3.13
Requires-Dist: joblib
Requires-Dist: matplotlib
Requires-Dist: numpy (>=1.21,<2.0)
Requires-Dist: pandas (>=2.0,<3.0)
Requires-Dist: pyvista
Requires-Dist: scipy
Requires-Dist: tqdm
